mcp_server/__init__.py
mcp_server/server.py
mcp_server-0.1.3.dist-info/METADATA
mcp_server-0.1.3.dist-info/WHEEL
mcp_server-0.1.3.dist-info/entry_points.txt
mcp_server-0.1.3.dist-info/RECORD
