Metadata-Version: 2.4
Name: mcp-server
Version: 0.1.3
Summary: A custom MCP server that provides useful tools and resources for AI assistants
Author-email: AjinkyaSambare <ajinkya@idealabs.fyi>
Requires-Python: >=3.13
Requires-Dist: mcp>=1.6.0
